pymedia/__init__.py
pymedia/ai.py
pymedia/cli.py
pymedia/pinterest.py
pymedia/shortcut.py
py_cdgram-0.2.0.dist-info/LICENSE
py_cdgram-0.2.0.dist-info/METADATA
py_cdgram-0.2.0.dist-info/WHEEL
py_cdgram-0.2.0.dist-info/entry_points.txt
py_cdgram-0.2.0.dist-info/top_level.txt
py_cdgram-0.2.0.dist-info/RECORD
